MEDimage/MEDscan.py
MEDimage/__init__.py
MEDimage/biomarkers/BatchExtractor.py
MEDimage/biomarkers/BatchExtractorTexturalFilters.py
MEDimage/biomarkers/__init__.py
MEDimage/biomarkers/diagnostics.py
MEDimage/biomarkers/get_oriented_bound_box.py
MEDimage/biomarkers/glcm.py
MEDimage/biomarkers/gldzm.py
MEDimage/biomarkers/glrlm.py
MEDimage/biomarkers/glszm.py
MEDimage/biomarkers/int_vol_hist.py
MEDimage/biomarkers/intensity_histogram.py
MEDimage/biomarkers/local_intensity.py
MEDimage/biomarkers/morph.py
MEDimage/biomarkers/ngldm.py
MEDimage/biomarkers/ngtdm.py
MEDimage/biomarkers/stats.py
MEDimage/biomarkers/utils.py
MEDimage/filters/TexturalFilter.py
MEDimage/filters/__init__.py
MEDimage/filters/apply_filter.py
MEDimage/filters/gabor.py
MEDimage/filters/laws.py
MEDimage/filters/log.py
MEDimage/filters/mean.py
MEDimage/filters/textural_filters_kernels.py
MEDimage/filters/utils.py
MEDimage/filters/wavelet.py
MEDimage/learning/DataCleaner.py
MEDimage/learning/DesignExperiment.py
MEDimage/learning/FSR.py
MEDimage/learning/Normalization.py
MEDimage/learning/RadiomicsLearner.py
MEDimage/learning/Results.py
MEDimage/learning/Stats.py
MEDimage/learning/__init__.py
MEDimage/learning/cleaning_utils.py
MEDimage/learning/ml_utils.py
MEDimage/processing/__init__.py
MEDimage/processing/compute_suv_map.py
MEDimage/processing/discretisation.py
MEDimage/processing/interpolation.py
MEDimage/processing/resegmentation.py
MEDimage/processing/segmentation.py
MEDimage/utils/__init__.py
MEDimage/utils/batch_patients.py
MEDimage/utils/create_radiomics_table.py
MEDimage/utils/data_frame_export.py
MEDimage/utils/find_process_names.py
MEDimage/utils/get_file_paths.py
MEDimage/utils/get_full_rad_names.py
MEDimage/utils/get_institutions_from_ids.py
MEDimage/utils/get_patient_id_from_scan_name.py
MEDimage/utils/get_patient_names.py
MEDimage/utils/get_radiomic_names.py
MEDimage/utils/get_scan_name_from_rad_name.py
MEDimage/utils/image_reader_SITK.py
MEDimage/utils/image_volume_obj.py
medimage_pkg-0.9.7.dist-info/LICENSE.md
medimage_pkg-0.9.7.dist-info/METADATA
medimage_pkg-0.9.7.dist-info/WHEEL
medimage_pkg-0.9.7.dist-info/RECORD
